anomalib/__init__.py
anomalib/config/__init__.py
anomalib/config/config.py
anomalib/data/__init__.py
anomalib/data/avenue.py
anomalib/data/base/__init__.py
anomalib/data/base/datamodule.py
anomalib/data/base/dataset.py
anomalib/data/base/depth.py
anomalib/data/base/video.py
anomalib/data/btech.py
anomalib/data/folder.py
anomalib/data/folder_3d.py
anomalib/data/inference.py
anomalib/data/kolektor.py
anomalib/data/mvtec.py
anomalib/data/mvtec_3d.py
anomalib/data/shanghaitech.py
anomalib/data/synthetic.py
anomalib/data/task_type.py
anomalib/data/ucsd_ped.py
anomalib/data/utils/__init__.py
anomalib/data/utils/augmenter.py
anomalib/data/utils/boxes.py
anomalib/data/utils/download.py
anomalib/data/utils/generators/__init__.py
anomalib/data/utils/generators/perlin.py
anomalib/data/utils/image.py
anomalib/data/utils/label.py
anomalib/data/utils/path.py
anomalib/data/utils/split.py
anomalib/data/utils/transform.py
anomalib/data/utils/video.py
anomalib/data/visa.py
anomalib/deploy/__init__.py
anomalib/deploy/export.py
anomalib/deploy/inferencers/__init__.py
anomalib/deploy/inferencers/base_inferencer.py
anomalib/deploy/inferencers/openvino_inferencer.py
anomalib/deploy/inferencers/torch_inferencer.py
anomalib/models/__init__.py
anomalib/models/ai_vad/__init__.py
anomalib/models/ai_vad/clip/LICENSE
anomalib/models/ai_vad/clip/__init__.py
anomalib/models/ai_vad/clip/clip.py
anomalib/models/ai_vad/clip/model.py
anomalib/models/ai_vad/config.yaml
anomalib/models/ai_vad/density.py
anomalib/models/ai_vad/features.py
anomalib/models/ai_vad/flow.py
anomalib/models/ai_vad/lightning_model.py
anomalib/models/ai_vad/regions.py
anomalib/models/ai_vad/torch_model.py
anomalib/models/cfa/README.md
anomalib/models/cfa/__init__.py
anomalib/models/cfa/anomaly_map.py
anomalib/models/cfa/config.yaml
anomalib/models/cfa/lightning_model.py
anomalib/models/cfa/loss.py
anomalib/models/cfa/torch_model.py
anomalib/models/cflow/README.md
anomalib/models/cflow/__init__.py
anomalib_orobix-0.7.0rc1421.dist-info/LICENSE
anomalib_orobix-0.7.0rc1421.dist-info/METADATA
anomalib_orobix-0.7.0rc1421.dist-info/WHEEL
anomalib_orobix-0.7.0rc1421.dist-info/RECORD
