Metadata-Version: 2.1
Name: anomalib-orobix
Version: 0.7.0rc1421
Summary: Orobix anomalib fork
Home-page: https://github.com/orobix/quadra
License: Apache-2.0
Author: Intel OpenVINO
Author-email: help@openvino.intel.com
Requires-Python: >=3.9,<3.11
Classifier: License :: OSI Approved :: Apache Software License
Classifier: Programming Language :: Python :: 3
Classifier: Programming Language :: Python :: 3.9
Classifier: Programming Language :: Python :: 3.10
Provides-Extra: augmentation
Requires-Dist: einops (>=0.6,<0.7)
Requires-Dist: freia (>=0.2,<0.3)
Requires-Dist: gradio (==3.0.2)
Requires-Dist: imgaug (==0.4.0) ; extra == "augmentation"
Requires-Dist: jsonargparse[signatures] (>=4.3.0,<4.4.0)
Requires-Dist: kornia (==0.6.5)
Requires-Dist: line-profiler (==3.5.1)
Requires-Dist: omegaconf (>=2.3,<2.4)
Requires-Dist: wandb (==0.12.17)
Project-URL: Repository, https://github.com/orobix/quadra
